termspark/__init__.py
termspark/py.typed
termspark/termspark.py
termspark/exceptions/__init__.py
termspark/exceptions/arg_chars_exceeded_error.py
termspark/exceptions/combination_error.py
termspark/exceptions/empty_error.py
termspark/exceptions/len_not_supported_error.py
termspark/exceptions/min_not_reached_error.py
termspark/exceptions/multiple_positions_not_supported_error.py
termspark/exceptions/parameter_type_error.py
termspark/exceptions/position_not_supported_error.py
termspark/exceptions/printer_arg_error.py
termspark/helpers/__init__.py
termspark/helpers/list.py
termspark/hyperlink/__init__.py
termspark/hyperlink/hyperlink.py
termspark/line/__init__.py
termspark/line/line.py
termspark/painter/__init__.py
termspark/painter/mode_manager.py
termspark/painter/painter.py
termspark/painter/constants/__init__.py
termspark/painter/constants/color.py
termspark/painter/constants/fore.py
termspark/painter/constants/highlight.py
termspark/painter/modes/__init__.py
termspark/painter/modes/hex.py
termspark/painter/modes/mode.py
termspark/painter/modes/name.py
termspark/painter/modes/rgb.py
termspark/separator/__init__.py
termspark/separator/separator.py
termspark/structurer/__init__.py
termspark/structurer/structurer.py
termspark/styler/__init__.py
termspark/styler/styler.py
termspark/text_styler/__init__.py
termspark/text_styler/text_styler.py
termspark/text_styler/constants/__init__.py
termspark/text_styler/constants/style.py
termspark/trimer/__init__.py
termspark/trimer/trimer.py
termspark/validators/__init__.py
termspark/validators/printer_validator.py
termspark-3.0.0.dist-info/LICENSE
termspark-3.0.0.dist-info/METADATA
termspark-3.0.0.dist-info/WHEEL
termspark-3.0.0.dist-info/top_level.txt
termspark-3.0.0.dist-info/RECORD
