Metadata-Version: 2.1
Name: termspark
Version: 3.0.0
Summary: Takes control of terminal
Home-page: https://github.com/faissaloux/termspark
Author: Faissal Wahabali
Author-email: contact@faissaloux.com
License: MIT
Keywords: terminal,cmd,design,colorful
Platform: UNKNOWN
Classifier: Development Status :: 5 - Production/Stable
Classifier: Programming Language :: Python :: 3.10
Classifier: Programming Language :: Python :: 3.11
Classifier: Programming Language :: Python :: 3.12
Classifier: Programming Language :: Python :: 3.13
Classifier: Programming Language :: Python :: 3.14
Classifier: Typing :: Typed
Classifier: License :: OSI Approved :: MIT License
Classifier: Operating System :: OS Independent
Requires-Python: <3.15,>=3.10
License-File: LICENSE
Requires-Dist: typing-extensions (>=4.15.0)
Provides-Extra: dev
Requires-Dist: pytest (>=9.0.0) ; extra == 'dev'
Requires-Dist: pytest-cov (>=7.0.0) ; extra == 'dev'
Requires-Dist: mypy (>=1.19.0) ; extra == 'dev'
Requires-Dist: pre-commit (>=4.5.0) ; extra == 'dev'
Requires-Dist: isort (>=7.0.0) ; extra == 'dev'
Requires-Dist: black (>=26.1.0) ; extra == 'dev'
Requires-Dist: mock (>=5.2.0) ; extra == 'dev'
Requires-Dist: types-mock (>=5.2.0) ; extra == 'dev'
Provides-Extra: docs
Requires-Dist: mkdocs (>=1.6.0) ; extra == 'docs'
Requires-Dist: mkdocs-material (>=9.7.1) ; extra == 'docs'
Requires-Dist: pymdown-extensions (>=10.20) ; extra == 'docs'
Requires-Dist: mike (>=2.1.3) ; extra == 'docs'
